adb_uninstall/__init__.py
adb_uninstall/__main__.py
adb_uninstall/adb_package.py
adb_uninstall/constants.py
adb_uninstall/gui.py
adb_uninstall/tk_automenu.py
adb_uninstall/tk_statusbar.py
adb_uninstall/utils/__init__.py
adb_uninstall/utils/humanize.py
adb_uninstall/utils/redirect.py
adb_uninstall/utils/subprocess2.py
PyAdbUninstall-0.3.0.dist-info/AUTHORS
PyAdbUninstall-0.3.0.dist-info/LICENSE
PyAdbUninstall-0.3.0.dist-info/METADATA
PyAdbUninstall-0.3.0.dist-info/WHEEL
PyAdbUninstall-0.3.0.dist-info/entry_points.txt
PyAdbUninstall-0.3.0.dist-info/top_level.txt
PyAdbUninstall-0.3.0.dist-info/RECORD
