Metadata-Version: 2.1
Name: PyAdbUninstall
Version: 0.3.0
Summary: Thinker GUI for uninstall Android bloatware Apps via 'adb' without root.
Home-page: https://github.com/jedie/PyAdbUninstall
Author: Jens Diemer
Author-email: pypi@jensdiemer.de
License: UNKNOWN
Platform: UNKNOWN
Classifier: Programming Language :: Python :: 3
Classifier: License :: OSI Approved :: GNU General Public License v3 or later (GPLv3+)
Classifier: Operating System :: OS Independent
Requires-Python: >=3.5
